{
  "1": {
    "title": "Yodha Jangchi",
    "parts": [
      {
        "title": "Yodha Jangchi",
        "description": "Hind filmi o'zbek tilida \nMaroqli tomasha tilaymiz",
        "video": "BAACAgQAAxkBAAMhaRdOeTQ0FC7nleWZujP9Zn8MF98AAg4TAAJB5ghS5QUWc_NVLHo2BA"
      }
    ],
    "views": 9
  },
  "2": {
    "title": "Jahannamda",
    "parts": [
      {
        "title": "Jahannamda",
        "description": "🌎 Davlati: AQSH\n💽 Formati: HD (720p)\n🇺🇿 Tili: O'zbekcha  \n📆 Sanasi: 2003",
        "video": "BAACAgIAAxkBAAM7aRdV3Lzu7EutyFAqJHuRnKysKzEAArgqAAKwpZhKRQGTMQr-dS42BA"
      }
    ],
    "views": 8
  },
  "3": {
    "title": "Sevgi bir lahzalik his",
    "parts": [
      {
        "title": "Sevgi bir lahzalik his",
        "description": "⚡️ Sifati: 1080p \n🌍 Davlati: Turkiya\n🌐 Tili: O‘zbek tlida\n📆 Yili: 2025",
        "video": "BAACAgQAAxkBAANHaRdZ7ZOkkTB5b6dfQjEPMxvGdcsAAo0YAAIzW7BQOAYMjQqgrb42BA"
      }
    ],
    "views": 7
  },
  "4": {
    "title": "Yashil qovoq ari",
    "parts": [
      {
        "title": "Yashil qovoq ari",
        "description": "Aqsh kinosi  \n\nTil: Uzbek tilida English aralash malum bir qismi",
        "video": "BAACAgQAAxkBAAIBaWkop3gaR1gSlScU1xvYoqzGUIkFAAIsFQACTn6pUCA-NAsPAjmDNgQ"
      }
    ],
    "views": 2
  },
  "5": {
    "title": "Parallel olamdagi muhabbat",
    "parts": [
      {
        "title": "Parallel olamdagi muhabbat",
        "description": "Ajoyib komedik va 18+ film.\n📽 Filmda ikki parallel olamdi juftlik bir birini yoqtirib qolishidi va o'zlari haqida turlicha tanishishadi.",
        "video": "BAACAgIAAxkBAAICoGkv3FN2nz_7a3eCxtwnsaLcPXlkAAKXhAACogZhSXt7M4kAAQpWTzYE"
      }
    ],
    "views": 0
  },
  "6": {
    "title": "Kichkina qahramon",
    "parts": [
      {
        "title": "Kichkina qahramon",
        "description": "Maroqli hordiq tilaymiz",
        "video": "BAACAgIAAxkBAAICp2kv4YgIstsd3vQTavFXXG34aVlXAANRAAJ6NwFL_lGYVQvbYIQ2BA"
      }
    ],
    "views": 0
  }
}
